genkit/plugins/dev_local_vectorstore/__init__.py
genkit/plugins/dev_local_vectorstore/constant.py
genkit/plugins/dev_local_vectorstore/indexer.py
genkit/plugins/dev_local_vectorstore/local_vector_store_api.py
genkit/plugins/dev_local_vectorstore/plugin_api.py
genkit/plugins/dev_local_vectorstore/retriever.py
genkit/plugins/dev_local_vectorstore/__init__.py
genkit/plugins/dev_local_vectorstore/constant.py
genkit/plugins/dev_local_vectorstore/indexer.py
genkit/plugins/dev_local_vectorstore/local_vector_store_api.py
genkit/plugins/dev_local_vectorstore/plugin_api.py
genkit/plugins/dev_local_vectorstore/retriever.py
genkit_plugin_dev_local_vectorstore-0.4.0.dist-info/METADATA
genkit_plugin_dev_local_vectorstore-0.4.0.dist-info/WHEEL
genkit_plugin_dev_local_vectorstore-0.4.0.dist-info/licenses/LICENSE
genkit_plugin_dev_local_vectorstore-0.4.0.dist-info/RECORD
